twitch_talkbot/__init__.py
twitch_talkbot/__main__.py
twitch_talkbot/command_processor.py
twitch_talkbot/config.py
twitch_talkbot/talkbot.py
twitch_talkbot/text_to_speech.py
twitch_talkbot/tts/__init__.py
twitch_talkbot/tts/pyttsx3_tts.py
twitch_talkbot-0.1.6.dist-info/METADATA
twitch_talkbot-0.1.6.dist-info/WHEEL
twitch_talkbot-0.1.6.dist-info/top_level.txt
twitch_talkbot-0.1.6.dist-info/RECORD
