Metadata-Version: 2.1
Name: twitch-talkbot
Version: 0.1.6
Summary: A twitch bot for streamers who can't / don't want to talk
Home-page: http://github.com/eriknyquist/twitch_talkbot
Author: Erik Nyquist
Author-email: eknyquist@gmail.com
License: Apache 2.0
Platform: UNKNOWN
Requires-Dist: pyttsx3
Requires-Dist: prompt-toolkit
Requires-Dist: twitchio
